pyams_layer/__init__.py
pyams_layer/include.py
pyams_layer/interfaces.py
pyams_layer/resources.py
pyams_layer/skin.py
pyams_layer/vocabulary.py
pyams_layer/doctests/README.rst
pyams_layer/locales/pyams_layer.pot
pyams_layer/locales/fr/LC_MESSAGES/pyams_layer.mo
pyams_layer/locales/fr/LC_MESSAGES/pyams_layer.po
pyams_layer/tests/__init__.py
pyams_layer/tests/test_utilsdocs.py
pyams_layer/tests/test_utilsdocstrings.py
pyams_layer-2.2.0.dist-info/LICENSE
pyams_layer-2.2.0.dist-info/METADATA
pyams_layer-2.2.0.dist-info/WHEEL
pyams_layer-2.2.0.dist-info/namespace_packages.txt
pyams_layer-2.2.0.dist-info/top_level.txt
pyams_layer-2.2.0.dist-info/RECORD
