Metadata-Version: 2.1
Name: pyams-layer
Version: 2.2.0
Summary: PyAMS base layers management
Home-page: https://pyams.readthedocs.io
Author: Thierry Florac
Author-email: tflorac@ulthar.net
License: ZPL
Keywords: Pyramid PyAMS
Classifier: License :: OSI Approved :: Zope Public License
Classifier: Development Status :: 4 - Beta
Classifier: Programming Language :: Python
Classifier: Framework :: Pyramid
Classifier: Topic :: Software Development :: Libraries :: Python Modules
Requires-Python: >=3.5
License-File: LICENSE
Requires-Dist: setuptools
Requires-Dist: pyams-file
Requires-Dist: pyams-security
Requires-Dist: pyams-site
Requires-Dist: pyams-utils
Requires-Dist: pyramid >=2.0.0
Requires-Dist: zope.componentvocabulary
Requires-Dist: zope.configuration
Requires-Dist: zope.dublincore
Requires-Dist: zope.interface
Requires-Dist: zope.schema
Requires-Dist: zope.traversing
Provides-Extra: test
Requires-Dist: pyramid-zcml ; extra == 'test'
Requires-Dist: zope.exceptions ; extra == 'test'
